argparseqt/groupingTools.py
argparseqt/gui.py
argparseqt/typeHelpers.py
argparseqt/wrappedWidgets.py
argparseqt-0.3.4.dist-info/LICENSE.txt
argparseqt-0.3.4.dist-info/METADATA
argparseqt-0.3.4.dist-info/WHEEL
argparseqt-0.3.4.dist-info/top_level.txt
argparseqt-0.3.4.dist-info/RECORD
