Metadata-Version: 2.1
Name: argparseqt
Version: 0.3.4
Summary: An easy way to make Qt GUIs using the argparse standard module
Home-page: https://github.com/domstoppable/argparseqt
Author: Dominic Canare
Author-email: dom@dominiccanare.com
License: MIT
License-File: LICENSE.txt
Requires-Dist: QtPy (>=1.7.0)
Requires-Dist: PySide2 (>=5.12.2)
